pylive/__init__.py
pylive/api/__init__.py
pylive/api/routes.py
pylive/auth/__init__.py
pylive/auth/jwt.py
pylive/chat/__init__.py
pylive/chat/dm_manager.py
pylive/chat/hub.py
pylive/cli/__init__.py
pylive/cli/main.py
pylive/core/__init__.py
pylive/core/config.py
pylive/core/server.py
pylive/realtime/__init__.py
pylive/realtime/channel.py
pylive/realtime/server.py
pylive/realtime/types.py
pylive/ui/__init__.py
pylive/ui/api.py
pylive/ui/app.py
pylive/ui/config.py
pylive/ui/state.py
pylive/ui/styles.py
pylive/ui/components/__init__.py
pylive/ui/components/cards.py
pylive/ui/components/message.py
pylive/ui/components/navbar.py
pylive/ui/pages/__init__.py
pylive/ui/pages/chat.py
pylive/ui/pages/login.py
pylive/ui/pages/messages.py
pylive/ui/pages/stats.py
pylive_realtime-1.0.0.dist-info/METADATA
pylive_realtime-1.0.0.dist-info/WHEEL
pylive_realtime-1.0.0.dist-info/entry_points.txt
pylive_realtime-1.0.0.dist-info/top_level.txt
pylive_realtime-1.0.0.dist-info/RECORD
