Metadata-Version: 2.4
Name: pylive-realtime
Version: 1.0.0
Summary: PyLive: Python Realtime Streaming Platform with WebSocket, SSE, Chat, DM
Home-page: https://github.com/Web3-League/pylive
Author: nano3
Author-email: 
License: MIT
Project-URL: Homepage, https://github.com/Web3-League/pylive
Project-URL: Documentation, https://github.com/Web3-League/pylive#readme
Project-URL: Repository, https://github.com/Web3-League/pylive
Project-URL: Issues, https://github.com/Web3-League/pylive/issues
Keywords: realtime,websocket,sse,chat,streaming,fastapi
Classifier: Development Status :: 4 - Beta
Classifier: Environment :: Console
Classifier: Environment :: Web Environment
Classifier: Framework :: FastAPI
Classifier: Intended Audience :: Developers
Classifier: License :: OSI Approved :: MIT License
Classifier: Operating System :: OS Independent
Classifier: Programming Language :: Python :: 3
Classifier: Programming Language :: Python :: 3.8
Classifier: Programming Language :: Python :: 3.9
Classifier: Programming Language :: Python :: 3.10
Classifier: Programming Language :: Python :: 3.11
Classifier: Programming Language :: Python :: 3.12
Classifier: Topic :: Communications :: Chat
Classifier: Topic :: Internet :: WWW/HTTP :: HTTP Servers
Requires-Python: >=3.8
Requires-Dist: fastapi>=0.100.0
Requires-Dist: uvicorn>=0.23.0
Requires-Dist: websockets>=11.0
Requires-Dist: pyjwt>=2.8.0
Requires-Dist: pydantic>=2.0.0
Requires-Dist: httpx>=0.24.0
Provides-Extra: ui
Requires-Dist: streamlit>=1.28.0; extra == "ui"
Requires-Dist: streamlit-shadcn-ui>=0.1.0; extra == "ui"
Requires-Dist: requests>=2.31.0; extra == "ui"
Requires-Dist: websocket-client>=1.6.0; extra == "ui"
Provides-Extra: dev
Requires-Dist: pytest>=7.0.0; extra == "dev"
Requires-Dist: pytest-asyncio>=0.21.0; extra == "dev"
Requires-Dist: black>=23.0.0; extra == "dev"
Requires-Dist: mypy>=1.0.0; extra == "dev"
Dynamic: home-page
Dynamic: requires-python
